setup.cfg
setup.py
pandass_plus/Shortcuts.py
pandass_plus/__init__.py
pandass_plus.egg-info/PKG-INFO
pandass_plus.egg-info/SOURCES.txt
pandass_plus.egg-info/dependency_links.txt
pandass_plus.egg-info/not-zip-safe
pandass_plus.egg-info/top_level.txt