Metadata-Version: 2.1
Name: pandass-plus
Version: 0.0.3
Summary: Taa
Author-email: serezha.belikov.05@mail.ru
